vllm/__init__.py
vllm/config.py
vllm/data.py
vllm/mask.py
vllm/train.py
vllm/transformer.py
vllm/blocks/__init__.py
vllm/blocks/common.py
vllm/blocks/decoder.py
vllm/blocks/embedding.py
vllm/blocks/encoder.py
vllm/blocks/multihead.py
visualLLM-0.1.0.dist-info/LICENSE
visualLLM-0.1.0.dist-info/METADATA
visualLLM-0.1.0.dist-info/WHEEL
visualLLM-0.1.0.dist-info/top_level.txt
visualLLM-0.1.0.dist-info/RECORD
